dtkit/__init__.py
dtkit/color.py
dtkit/temperature.py
DTKit-0.3.dist-info/LICENSE
DTKit-0.3.dist-info/METADATA
DTKit-0.3.dist-info/WHEEL
DTKit-0.3.dist-info/top_level.txt
DTKit-0.3.dist-info/RECORD
