Metadata-Version: 2.1
Name: DTKit
Version: 0.3
Summary: A package that offers new data types to use in everyday Python use.
Author: Chase Galloway
Author-email: chase.h.galloway21@gmail.com
Classifier: Programming Language :: Python :: 3
Classifier: License :: OSI Approved :: MIT License
Classifier: Operating System :: OS Independent
Requires-Python: >=3.6
License-File: LICENSE
